{
  "collectionName": "components_ui_card_items",
  "info": {
    "displayName": "Card Item",
    "description": ""
  },
  "options": {},
  "attributes": {
    "Imagem": {
      "type": "media",
      "multiple": false,
      "required": false,
      "allowedTypes": [
        "images"
      ]
    },
    "Content": {
      "type": "customField",
      "options": {
        "preset": "defaultHtml"
      },
      "required": true,
      "customField": "plugin::ckeditor5.CKEditor"
    },
    "aspectRatio": {
      "type": "enumeration",
      "enum": [
        "Medium Format",
        "Standard",
        "Square",
        "Classic",
        "Widescreen",
        "Vertical Portrait",
        "Cinemascope Panoramic"
      ],
      "required": false,
      "default": "Medium Format"
    }
  }
}
